README.rst
setup.py
django_auth_email/__init__.py
django_auth_email/admin.py
django_auth_email/apps.py
django_auth_email/models.py
django_auth_email/tests.py
django_auth_email/views.py
django_auth_email.egg-info/PKG-INFO
django_auth_email.egg-info/SOURCES.txt
django_auth_email.egg-info/dependency_links.txt
django_auth_email.egg-info/top_level.txt